Workbook

Sheet Mode d'emploi
A1: La Tendresse de Ketchup — Classeur de pilotage
A2: Restaurant-Bar · Quartier Diata, Brazzaville
A4: Principe | B4: Les cellules BLANCHES se saisissent. Les cellules CRÈME se calculent toutes seules : ne pas les effacer.
A5: 1. Paramètres | B5: Saisir le fonds de caisse de départ, la liste du personnel et l'année suivie.
A6: 2. Caisse | B6: Chaque soir, recopier les pièces de caisse (entrées/sorties) et les ventes du jour (une ligne par mode de paiement).
A7: 3. Clôtures | B7: Chaque soir, reporter le solde théorique et les espèces comptées de la fiche de clôture : l'écart se calcule.
A8: 4. Stocks | B8: Une ligne par article. Chaque semaine, saisir les entrées, sorties et le stock compté de l'inventaire.
A9: 5. Crédits | B9: Reporter le registre des crédits clients. Le statut (soldé / en retard) se met à jour seul.
A10: 6. Avances | B10: Reporter les bons d'avance sur salaire.
A11: 7. Tableau de bord | B11: Rien à saisir : synthèse mensuelle automatique + graphique. À présenter chaque mois à la Direction.
A12: Règle d'or | B12: Pas d'argent qui entre ou qui sort sans papier. Un papier = une ligne dans ce classeur.

Sheet Tableau de bord
A1: La Tendresse de Ketchup — Tableau de bord
A2: Calcul automatique à partir des onglets Caisse, Clôtures, Stocks, Crédits et Avances.
A4: Mois | B4: Ventes FCFA | C4: Autres entrées FCFA | D4: Dépenses FCFA | E4: Résultat FCFA | F4: Résultat / ventes | G4: Écarts de caisse FCFA | H4: Avances FCFA | I4: Achat boissons | J4: Achat cuisine / denrées | K4: Salaire / avance | L4: Loyer | M4: Électricité / eau | N4: Transport | O4: Entretien / réparation | P4: Taxes / mairie | Q4: Autre dépense
A5: Janvier | B5: =SUMIFS(Caisse!$G$5:$G$604,Caisse!$D$5:$D$604,"Ventes du jour",Caisse!$J$5:$J$604,1,Caisse!$A$5:$A$604,">="&DATE(Paramètres!$B$4,1,1),Caisse!$A$5:$A$604,"<="&DATE(Paramètres!$B$4,12,31)) | C5: =SUMIFS(Caisse!$G$5:$G$604,Caisse!$J$5:$J$604,1,Caisse!$A$5:$A$604,">="&DATE(Paramètres!$B$4,1,1),Caisse!$A$5:$A$604,"<="&DATE(Paramètres!$B$4,12,31))-B5 | D5: =SUMIFS(Caisse!$H$5:$H$604,Caisse!$J$5:$J$604,1,Caisse!$A$5:$A$604,">="&DATE(Paramètres!$B$4,1,1),Caisse!$A$5:$A$604,"<="&DATE(Paramètres!$B$4,12,31)) | E5: =B5+C5-D5 | F5: =IF(B5=0,"",E5/B5) | G5: =SUMIFS(Clôtures!$E$5:$E$404,Clôtures!$I$5:$I$404,1,Clôtures!$A$5:$A$404,">="&DATE(Paramètres!$B$4,1,1),Clôtures!$A$5:$A$404,"<="&DATE(Paramètres!$B$4,12,31)) | H5: =SUMIFS(Avances!$D$5:$D$304,Avances!$G$5:$G$304,1,Avances!$A$5:$A$304,">="&DATE(Paramètres!$B$4,1,1),Avances!$A$5:$A$304,"<="&DATE(Paramètres!$B$4,12,31)) | I5: =SUMIFS(Caisse!$H$5:$H$604,Caisse!$D$5:$D$604,"Achat boissons",Caisse!$J$5:$J$604,1,Caisse!$A$5:$A$604,">="&DATE(Paramètres!$B$4,1,1),Caisse!$A$5:$A$604,"<="&DATE(Paramètres!$B$4,12,31)) | J5: =SUMIFS(Caisse!$H$5:$H$604,Caisse!$D$5:$D$604,"Achat cuisine / denrées",Caisse!$J$5:$J$604,1,Caisse!$A$5:$A$604,">="&DATE(Paramètres!$B$4,1,1),Caisse!$A$5:$A$604,"<="&DATE(Paramètres!$B$4,12,31)) | K5: =SUMIFS(Caisse!$H$5:$H$604,Caisse!$D$5:$D$604,"Salaire / avance",Caisse!$J$5:$J$604,1,Caisse!$A$5:$A$604,">="&DATE(Paramètres!$B$4,1,1),Caisse!$A$5:$A$604,"<="&DATE(Paramètres!$B$4,12,31)) | L5: =SUMIFS(Caisse!$H$5:$H$604,Caisse!$D$5:$D$604,"Loyer",Caisse!$J$5:$J$604,1,Caisse!$A$5:$A$604,">="&DATE(Paramètres!$B$4,1,1),Caisse!$A$5:$A$604,"<="&DATE(Paramètres!$B$4,12,31)) | M5: =SUMIFS(Caisse!$H$5:$H$604,Caisse!$D$5:$D$604,"Électricité / eau",Caisse!$J$5:$J$604,1,Caisse!$A$5:$A$604,">="&DATE(Paramètres!$B$4,1,1),Caisse!$A$5:$A$604,"<="&DATE(Paramètres!$B$4,12,31)) | N5: =SUMIFS(Caisse!$H$5:$H$604,Caisse!$D$5:$D$604,"Transport",Caisse!$J$5:$J$604,1,Caisse!$A$5:$A$604,">="&DATE(Paramètres!$B$4,1,1),Caisse!$A$5:$A$604,"<="&DATE(Paramètres!$B$4,12,31)) | O5: =SUMIFS(Caisse!$H$5:$H$604,Caisse!$D$5:$D$604,"Entretien / réparation",Caisse!$J$5:$J$604,1,Caisse!$A$5:$A$604,">="&DATE(Paramètres!$B$4,1,1),Caisse!$A$5:$A$604,"<="&DATE(Paramètres!$B$4,12,31)) | P5: =SUMIFS(Caisse!$H$5:$H$604,Caisse!$D$5:$D$604,"Taxes / mairie",Caisse!$J$5:$J$604,1,Caisse!$A$5:$A$604,">="&DATE(Paramètres!$B$4,1,1),Caisse!$A$5:$A$604,"<="&DATE(Paramètres!$B$4,12,31)) | Q5: =SUMIFS(Caisse!$H$5:$H$604,Caisse!$D$5:$D$604,"Autre dépense",Caisse!$J$5:$J$604,1,Caisse!$A$5:$A$604,">="&DATE(Paramètres!$B$4,1,1),Caisse!$A$5:$A$604,"<="&DATE(Paramètres!$B$4,12,31))
A6: Février | B6: =SUMIFS(Caisse!$G$5:$G$604,Caisse!$D$5:$D$604,"Ventes du jour",Caisse!$J$5:$J$604,2,Caisse!$A$5:$A$604,">="&DATE(Paramètres!$B$4,1,1),Caisse!$A$5:$A$604,"<="&DATE(Paramètres!$B$4,12,31)) | C6: =SUMIFS(Caisse!$G$5:$G$604,Caisse!$J$5:$J$604,2,Caisse!$A$5:$A$604,">="&DATE(Paramètres!$B$4,1,1),Caisse!$A$5:$A$604,"<="&DATE(Paramètres!$B$4,12,31))-B6 | D6: =SUMIFS(Caisse!$H$5:$H$604,Caisse!$J$5:$J$604,2,Caisse!$A$5:$A$604,">="&DATE(Paramètres!$B$4,1,1),Caisse!$A$5:$A$604,"<="&DATE(Paramètres!$B$4,12,31)) | E6: =B6+C6-D6 | F6: =IF(B6=0,"",E6/B6) | G6: =SUMIFS(Clôtures!$E$5:$E$404,Clôtures!$I$5:$I$404,2,Clôtures!$A$5:$A$404,">="&DATE(Paramètres!$B$4,1,1),Clôtures!$A$5:$A$404,"<="&DATE(Paramètres!$B$4,12,31)) | H6: =SUMIFS(Avances!$D$5:$D$304,Avances!$G$5:$G$304,2,Avances!$A$5:$A$304,">="&DATE(Paramètres!$B$4,1,1),Avances!$A$5:$A$304,"<="&DATE(Paramètres!$B$4,12,31)) | I6: =SUMIFS(Caisse!$H$5:$H$604,Caisse!$D$5:$D$604,"Achat boissons",Caisse!$J$5:$J$604,2,Caisse!$A$5:$A$604,">="&DATE(Paramètres!$B$4,1,1),Caisse!$A$5:$A$604,"<="&DATE(Paramètres!$B$4,12,31)) | J6: =SUMIFS(Caisse!$H$5:$H$604,Caisse!$D$5:$D$604,"Achat cuisine / denrées",Caisse!$J$5:$J$604,2,Caisse!$A$5:$A$604,">="&DATE(Paramètres!$B$4,1,1),Caisse!$A$5:$A$604,"<="&DATE(Paramètres!$B$4,12,31)) | K6: =SUMIFS(Caisse!$H$5:$H$604,Caisse!$D$5:$D$604,"Salaire / avance",Caisse!$J$5:$J$604,2,Caisse!$A$5:$A$604,">="&DATE(Paramètres!$B$4,1,1),Caisse!$A$5:$A$604,"<="&DATE(Paramètres!$B$4,12,31)) | L6: =SUMIFS(Caisse!$H$5:$H$604,Caisse!$D$5:$D$604,"Loyer",Caisse!$J$5:$J$604,2,Caisse!$A$5:$A$604,">="&DATE(Paramètres!$B$4,1,1),Caisse!$A$5:$A$604,"<="&DATE(Paramètres!$B$4,12,31)) | M6: =SUMIFS(Caisse!$H$5:$H$604,Caisse!$D$5:$D$604,"Électricité / eau",Caisse!$J$5:$J$604,2,Caisse!$A$5:$A$604,">="&DATE(Paramètres!$B$4,1,1),Caisse!$A$5:$A$604,"<="&DATE(Paramètres!$B$4,12,31)) | N6: =SUMIFS(Caisse!$H$5:$H$604,Caisse!$D$5:$D$604,"Transport",Caisse!$J$5:$J$604,2,Caisse!$A$5:$A$604,">="&DATE(Paramètres!$B$4,1,1),Caisse!$A$5:$A$604,"<="&DATE(Paramètres!$B$4,12,31)) | O6: =SUMIFS(Caisse!$H$5:$H$604,Caisse!$D$5:$D$604,"Entretien / réparation",Caisse!$J$5:$J$604,2,Caisse!$A$5:$A$604,">="&DATE(Paramètres!$B$4,1,1),Caisse!$A$5:$A$604,"<="&DATE(Paramètres!$B$4,12,31)) | P6: =SUMIFS(Caisse!$H$5:$H$604,Caisse!$D$5:$D$604,"Taxes / mairie",Caisse!$J$5:$J$604,2,Caisse!$A$5:$A$604,">="&DATE(Paramètres!$B$4,1,1),Caisse!$A$5:$A$604,"<="&DATE(Paramètres!$B$4,12,31)) | Q6: =SUMIFS(Caisse!$H$5:$H$604,Caisse!$D$5:$D$604,"Autre dépense",Caisse!$J$5:$J$604,2,Caisse!$A$5:$A$604,">="&DATE(Paramètres!$B$4,1,1),Caisse!$A$5:$A$604,"<="&DATE(Paramètres!$B$4,12,31))
A7: Mars | B7: =SUMIFS(Caisse!$G$5:$G$604,Caisse!$D$5:$D$604,"Ventes du jour",Caisse!$J$5:$J$604,3,Caisse!$A$5:$A$604,">="&DATE(Paramètres!$B$4,1,1),Caisse!$A$5:$A$604,"<="&DATE(Paramètres!$B$4,12,31)) | C7: =SUMIFS(Caisse!$G$5:$G$604,Caisse!$J$5:$J$604,3,Caisse!$A$5:$A$604,">="&DATE(Paramètres!$B$4,1,1),Caisse!$A$5:$A$604,"<="&DATE(Paramètres!$B$4,12,31))-B7 | D7: =SUMIFS(Caisse!$H$5:$H$604,Caisse!$J$5:$J$604,3,Caisse!$A$5:$A$604,">="&DATE(Paramètres!$B$4,1,1),Caisse!$A$5:$A$604,"<="&DATE(Paramètres!$B$4,12,31)) | E7: =B7+C7-D7 | F7: =IF(B7=0,"",E7/B7) | G7: =SUMIFS(Clôtures!$E$5:$E$404,Clôtures!$I$5:$I$404,3,Clôtures!$A$5:$A$404,">="&DATE(Paramètres!$B$4,1,1),Clôtures!$A$5:$A$404,"<="&DATE(Paramètres!$B$4,12,31)) | H7: =SUMIFS(Avances!$D$5:$D$304,Avances!$G$5:$G$304,3,Avances!$A$5:$A$304,">="&DATE(Paramètres!$B$4,1,1),Avances!$A$5:$A$304,"<="&DATE(Paramètres!$B$4,12,31)) | I7: =SUMIFS(Caisse!$H$5:$H$604,Caisse!$D$5:$D$604,"Achat boissons",Caisse!$J$5:$J$604,3,Caisse!$A$5:$A$604,">="&DATE(Paramètres!$B$4,1,1),Caisse!$A$5:$A$604,"<="&DATE(Paramètres!$B$4,12,31)) | J7: =SUMIFS(Caisse!$H$5:$H$604,Caisse!$D$5:$D$604,"Achat cuisine / denrées",Caisse!$J$5:$J$604,3,Caisse!$A$5:$A$604,">="&DATE(Paramètres!$B$4,1,1),Caisse!$A$5:$A$604,"<="&DATE(Paramètres!$B$4,12,31)) | K7: =SUMIFS(Caisse!$H$5:$H$604,Caisse!$D$5:$D$604,"Salaire / avance",Caisse!$J$5:$J$604,3,Caisse!$A$5:$A$604,">="&DATE(Paramètres!$B$4,1,1),Caisse!$A$5:$A$604,"<="&DATE(Paramètres!$B$4,12,31)) | L7: =SUMIFS(Caisse!$H$5:$H$604,Caisse!$D$5:$D$604,"Loyer",Caisse!$J$5:$J$604,3,Caisse!$A$5:$A$604,">="&DATE(Paramètres!$B$4,1,1),Caisse!$A$5:$A$604,"<="&DATE(Paramètres!$B$4,12,31)) | M7: =SUMIFS(Caisse!$H$5:$H$604,Caisse!$D$5:$D$604,"Électricité / eau",Caisse!$J$5:$J$604,3,Caisse!$A$5:$A$604,">="&DATE(Paramètres!$B$4,1,1),Caisse!$A$5:$A$604,"<="&DATE(Paramètres!$B$4,12,31)) | N7: =SUMIFS(Caisse!$H$5:$H$604,Caisse!$D$5:$D$604,"Transport",Caisse!$J$5:$J$604,3,Caisse!$A$5:$A$604,">="&DATE(Paramètres!$B$4,1,1),Caisse!$A$5:$A$604,"<="&DATE(Paramètres!$B$4,12,31)) | O7: =SUMIFS(Caisse!$H$5:$H$604,Caisse!$D$5:$D$604,"Entretien / réparation",Caisse!$J$5:$J$604,3,Caisse!$A$5:$A$604,">="&DATE(Paramètres!$B$4,1,1),Caisse!$A$5:$A$604,"<="&DATE(Paramètres!$B$4,12,31)) | P7: =SUMIFS(Caisse!$H$5:$H$604,Caisse!$D$5:$D$604,"Taxes / mairie",Caisse!$J$5:$J$604,3,Caisse!$A$5:$A$604,">="&DATE(Paramètres!$B$4,1,1),Caisse!$A$5:$A$604,"<="&DATE(Paramètres!$B$4,12,31)) | Q7: =SUMIFS(Caisse!$H$5:$H$604,Caisse!$D$5:$D$604,"Autre dépense",Caisse!$J$5:$J$604,3,Caisse!$A$5:$A$604,">="&DATE(Paramètres!$B$4,1,1),Caisse!$A$5:$A$604,"<="&DATE(Paramètres!$B$4,12,31))
A8: Avril | B8: =SUMIFS(Caisse!$G$5:$G$604,Caisse!$D$5:$D$604,"Ventes du jour",Caisse!$J$5:$J$604,4,Caisse!$A$5:$A$604,">="&DATE(Paramètres!$B$4,1,1),Caisse!$A$5:$A$604,"<="&DATE(Paramètres!$B$4,12,31)) | C8: =SUMIFS(Caisse!$G$5:$G$604,Caisse!$J$5:$J$604,4,Caisse!$A$5:$A$604,">="&DATE(Paramètres!$B$4,1,1),Caisse!$A$5:$A$604,"<="&DATE(Paramètres!$B$4,12,31))-B8 | D8: =SUMIFS(Caisse!$H$5:$H$604,Caisse!$J$5:$J$604,4,Caisse!$A$5:$A$604,">="&DATE(Paramètres!$B$4,1,1),Caisse!$A$5:$A$604,"<="&DATE(Paramètres!$B$4,12,31)) | E8: =B8+C8-D8 | F8: =IF(B8=0,"",E8/B8) | G8: =SUMIFS(Clôtures!$E$5:$E$404,Clôtures!$I$5:$I$404,4,Clôtures!$A$5:$A$404,">="&DATE(Paramètres!$B$4,1,1),Clôtures!$A$5:$A$404,"<="&DATE(Paramètres!$B$4,12,31)) | H8: =SUMIFS(Avances!$D$5:$D$304,Avances!$G$5:$G$304,4,Avances!$A$5:$A$304,">="&DATE(Paramètres!$B$4,1,1),Avances!$A$5:$A$304,"<="&DATE(Paramètres!$B$4,12,31)) | I8: =SUMIFS(Caisse!$H$5:$H$604,Caisse!$D$5:$D$604,"Achat boissons",Caisse!$J$5:$J$604,4,Caisse!$A$5:$A$604,">="&DATE(Paramètres!$B$4,1,1),Caisse!$A$5:$A$604,"<="&DATE(Paramètres!$B$4,12,31)) | J8: =SUMIFS(Caisse!$H$5:$H$604,Caisse!$D$5:$D$604,"Achat cuisine / denrées",Caisse!$J$5:$J$604,4,Caisse!$A$5:$A$604,">="&DATE(Paramètres!$B$4,1,1),Caisse!$A$5:$A$604,"<="&DATE(Paramètres!$B$4,12,31)) | K8: =SUMIFS(Caisse!$H$5:$H$604,Caisse!$D$5:$D$604,"Salaire / avance",Caisse!$J$5:$J$604,4,Caisse!$A$5:$A$604,">="&DATE(Paramètres!$B$4,1,1),Caisse!$A$5:$A$604,"<="&DATE(Paramètres!$B$4,12,31)) | L8: =SUMIFS(Caisse!$H$5:$H$604,Caisse!$D$5:$D$604,"Loyer",Caisse!$J$5:$J$604,4,Caisse!$A$5:$A$604,">="&DATE(Paramètres!$B$4,1,1),Caisse!$A$5:$A$604,"<="&DATE(Paramètres!$B$4,12,31)) | M8: =SUMIFS(Caisse!$H$5:$H$604,Caisse!$D$5:$D$604,"Électricité / eau",Caisse!$J$5:$J$604,4,Caisse!$A$5:$A$604,">="&DATE(Paramètres!$B$4,1,1),Caisse!$A$5:$A$604,"<="&DATE(Paramètres!$B$4,12,31)) | N8: =SUMIFS(Caisse!$H$5:$H$604,Caisse!$D$5:$D$604,"Transport",Caisse!$J$5:$J$604,4,Caisse!$A$5:$A$604,">="&DATE(Paramètres!$B$4,1,1),Caisse!$A$5:$A$604,"<="&DATE(Paramètres!$B$4,12,31)) | O8: =SUMIFS(Caisse!$H$5:$H$604,Caisse!$D$5:$D$604,"Entretien / réparation",Caisse!$J$5:$J$604,4,Caisse!$A$5:$A$604,">="&DATE(Paramètres!$B$4,1,1),Caisse!$A$5:$A$604,"<="&DATE(Paramètres!$B$4,12,31)) | P8: =SUMIFS(Caisse!$H$5:$H$604,Caisse!$D$5:$D$604,"Taxes / mairie",Caisse!$J$5:$J$604,4,Caisse!$A$5:$A$604,">="&DATE(Paramètres!$B$4,1,1),Caisse!$A$5:$A$604,"<="&DATE(Paramètres!$B$4,12,31)) | Q8: =SUMIFS(Caisse!$H$5:$H$604,Caisse!$D$5:$D$604,"Autre dépense",Caisse!$J$5:$J$604,4,Caisse!$A$5:$A$604,">="&DATE(Paramètres!$B$4,1,1),Caisse!$A$5:$A$604,"<="&DATE(Paramètres!$B$4,12,31))
A9: Mai | B9: =SUMIFS(Caisse!$G$5:$G$604,Caisse!$D$5:$D$604,"Ventes du jour",Caisse!$J$5:$J$604,5,Caisse!$A$5:$A$604,">="&DATE(Paramètres!$B$4,1,1),Caisse!$A$5:$A$604,"<="&DATE(Paramètres!$B$4,12,31)) | C9: =SUMIFS(Caisse!$G$5:$G$604,Caisse!$J$5:$J$604,5,Caisse!$A$5:$A$604,">="&DATE(Paramètres!$B$4,1,1),Caisse!$A$5:$A$604,"<="&DATE(Paramètres!$B$4,12,31))-B9 | D9: =SUMIFS(Caisse!$H$5:$H$604,Caisse!$J$5:$J$604,5,Caisse!$A$5:$A$604,">="&DATE(Paramètres!$B$4,1,1),Caisse!$A$5:$A$604,"<="&DATE(Paramètres!$B$4,12,31)) | E9: =B9+C9-D9 | F9: =IF(B9=0,"",E9/B9) | G9: =SUMIFS(Clôtures!$E$5:$E$404,Clôtures!$I$5:$I$404,5,Clôtures!$A$5:$A$404,">="&DATE(Paramètres!$B$4,1,1),Clôtures!$A$5:$A$404,"<="&DATE(Paramètres!$B$4,12,31)) | H9: =SUMIFS(Avances!$D$5:$D$304,Avances!$G$5:$G$304,5,Avances!$A$5:$A$304,">="&DATE(Paramètres!$B$4,1,1),Avances!$A$5:$A$304,"<="&DATE(Paramètres!$B$4,12,31)) | I9: =SUMIFS(Caisse!$H$5:$H$604,Caisse!$D$5:$D$604,"Achat boissons",Caisse!$J$5:$J$604,5,Caisse!$A$5:$A$604,">="&DATE(Paramètres!$B$4,1,1),Caisse!$A$5:$A$604,"<="&DATE(Paramètres!$B$4,12,31)) | J9: =SUMIFS(Caisse!$H$5:$H$604,Caisse!$D$5:$D$604,"Achat cuisine / denrées",Caisse!$J$5:$J$604,5,Caisse!$A$5:$A$604,">="&DATE(Paramètres!$B$4,1,1),Caisse!$A$5:$A$604,"<="&DATE(Paramètres!$B$4,12,31)) | K9: =SUMIFS(Caisse!$H$5:$H$604,Caisse!$D$5:$D$604,"Salaire / avance",Caisse!$J$5:$J$604,5,Caisse!$A$5:$A$604,">="&DATE(Paramètres!$B$4,1,1),Caisse!$A$5:$A$604,"<="&DATE(Paramètres!$B$4,12,31)) | L9: =SUMIFS(Caisse!$H$5:$H$604,Caisse!$D$5:$D$604,"Loyer",Caisse!$J$5:$J$604,5,Caisse!$A$5:$A$604,">="&DATE(Paramètres!$B$4,1,1),Caisse!$A$5:$A$604,"<="&DATE(Paramètres!$B$4,12,31)) | M9: =SUMIFS(Caisse!$H$5:$H$604,Caisse!$D$5:$D$604,"Électricité / eau",Caisse!$J$5:$J$604,5,Caisse!$A$5:$A$604,">="&DATE(Paramètres!$B$4,1,1),Caisse!$A$5:$A$604,"<="&DATE(Paramètres!$B$4,12,31)) | N9: =SUMIFS(Caisse!$H$5:$H$604,Caisse!$D$5:$D$604,"Transport",Caisse!$J$5:$J$604,5,Caisse!$A$5:$A$604,">="&DATE(Paramètres!$B$4,1,1),Caisse!$A$5:$A$604,"<="&DATE(Paramètres!$B$4,12,31)) | O9: =SUMIFS(Caisse!$H$5:$H$604,Caisse!$D$5:$D$604,"Entretien / réparation",Caisse!$J$5:$J$604,5,Caisse!$A$5:$A$604,">="&DATE(Paramètres!$B$4,1,1),Caisse!$A$5:$A$604,"<="&DATE(Paramètres!$B$4,12,31)) | P9: =SUMIFS(Caisse!$H$5:$H$604,Caisse!$D$5:$D$604,"Taxes / mairie",Caisse!$J$5:$J$604,5,Caisse!$A$5:$A$604,">="&DATE(Paramètres!$B$4,1,1),Caisse!$A$5:$A$604,"<="&DATE(Paramètres!$B$4,12,31)) | Q9: =SUMIFS(Caisse!$H$5:$H$604,Caisse!$D$5:$D$604,"Autre dépense",Caisse!$J$5:$J$604,5,Caisse!$A$5:$A$604,">="&DATE(Paramètres!$B$4,1,1),Caisse!$A$5:$A$604,"<="&DATE(Paramètres!$B$4,12,31))
A10: Juin | B10: =SUMIFS(Caisse!$G$5:$G$604,Caisse!$D$5:$D$604,"Ventes du jour",Caisse!$J$5:$J$604,6,Caisse!$A$5:$A$604,">="&DATE(Paramètres!$B$4,1,1),Caisse!$A$5:$A$604,"<="&DATE(Paramètres!$B$4,12,31)) | C10: =SUMIFS(Caisse!$G$5:$G$604,Caisse!$J$5:$J$604,6,Caisse!$A$5:$A$604,">="&DATE(Paramètres!$B$4,1,1),Caisse!$A$5:$A$604,"<="&DATE(Paramètres!$B$4,12,31))-B10 | D10: =SUMIFS(Caisse!$H$5:$H$604,Caisse!$J$5:$J$604,6,Caisse!$A$5:$A$604,">="&DATE(Paramètres!$B$4,1,1),Caisse!$A$5:$A$604,"<="&DATE(Paramètres!$B$4,12,31)) | E10: =B10+C10-D10 | F10: =IF(B10=0,"",E10/B10) | G10: =SUMIFS(Clôtures!$E$5:$E$404,Clôtures!$I$5:$I$404,6,Clôtures!$A$5:$A$404,">="&DATE(Paramètres!$B$4,1,1),Clôtures!$A$5:$A$404,"<="&DATE(Paramètres!$B$4,12,31)) | H10: =SUMIFS(Avances!$D$5:$D$304,Avances!$G$5:$G$304,6,Avances!$A$5:$A$304,">="&DATE(Paramètres!$B$4,1,1),Avances!$A$5:$A$304,"<="&DATE(Paramètres!$B$4,12,31)) | I10: =SUMIFS(Caisse!$H$5:$H$604,Caisse!$D$5:$D$604,"Achat boissons",Caisse!$J$5:$J$604,6,Caisse!$A$5:$A$604,">="&DATE(Paramètres!$B$4,1,1),Caisse!$A$5:$A$604,"<="&DATE(Paramètres!$B$4,12,31)) | J10: =SUMIFS(Caisse!$H$5:$H$604,Caisse!$D$5:$D$604,"Achat cuisine / denrées",Caisse!$J$5:$J$604,6,Caisse!$A$5:$A$604,">="&DATE(Paramètres!$B$4,1,1),Caisse!$A$5:$A$604,"<="&DATE(Paramètres!$B$4,12,31)) | K10: =SUMIFS(Caisse!$H$5:$H$604,Caisse!$D$5:$D$604,"Salaire / avance",Caisse!$J$5:$J$604,6,Caisse!$A$5:$A$604,">="&DATE(Paramètres!$B$4,1,1),Caisse!$A$5:$A$604,"<="&DATE(Paramètres!$B$4,12,31)) | L10: =SUMIFS(Caisse!$H$5:$H$604,Caisse!$D$5:$D$604,"Loyer",Caisse!$J$5:$J$604,6,Caisse!$A$5:$A$604,">="&DATE(Paramètres!$B$4,1,1),Caisse!$A$5:$A$604,"<="&DATE(Paramètres!$B$4,12,31)) | M10: =SUMIFS(Caisse!$H$5:$H$604,Caisse!$D$5:$D$604,"Électricité / eau",Caisse!$J$5:$J$604,6,Caisse!$A$5:$A$604,">="&DATE(Paramètres!$B$4,1,1),Caisse!$A$5:$A$604,"<="&DATE(Paramètres!$B$4,12,31)) | N10: =SUMIFS(Caisse!$H$5:$H$604,Caisse!$D$5:$D$604,"Transport",Caisse!$J$5:$J$604,6,Caisse!$A$5:$A$604,">="&DATE(Paramètres!$B$4,1,1),Caisse!$A$5:$A$604,"<="&DATE(Paramètres!$B$4,12,31)) | O10: =SUMIFS(Caisse!$H$5:$H$604,Caisse!$D$5:$D$604,"Entretien / réparation",Caisse!$J$5:$J$604,6,Caisse!$A$5:$A$604,">="&DATE(Paramètres!$B$4,1,1),Caisse!$A$5:$A$604,"<="&DATE(Paramètres!$B$4,12,31)) | P10: =SUMIFS(Caisse!$H$5:$H$604,Caisse!$D$5:$D$604,"Taxes / mairie",Caisse!$J$5:$J$604,6,Caisse!$A$5:$A$604,">="&DATE(Paramètres!$B$4,1,1),Caisse!$A$5:$A$604,"<="&DATE(Paramètres!$B$4,12,31)) | Q10: =SUMIFS(Caisse!$H$5:$H$604,Caisse!$D$5:$D$604,"Autre dépense",Caisse!$J$5:$J$604,6,Caisse!$A$5:$A$604,">="&DATE(Paramètres!$B$4,1,1),Caisse!$A$5:$A$604,"<="&DATE(Paramètres!$B$4,12,31))
A11: Juillet | B11: =SUMIFS(Caisse!$G$5:$G$604,Caisse!$D$5:$D$604,"Ventes du jour",Caisse!$J$5:$J$604,7,Caisse!$A$5:$A$604,">="&DATE(Paramètres!$B$4,1,1),Caisse!$A$5:$A$604,"<="&DATE(Paramètres!$B$4,12,31)) | C11: =SUMIFS(Caisse!$G$5:$G$604,Caisse!$J$5:$J$604,7,Caisse!$A$5:$A$604,">="&DATE(Paramètres!$B$4,1,1),Caisse!$A$5:$A$604,"<="&DATE(Paramètres!$B$4,12,31))-B11 | D11: =SUMIFS(Caisse!$H$5:$H$604,Caisse!$J$5:$J$604,7,Caisse!$A$5:$A$604,">="&DATE(Paramètres!$B$4,1,1),Caisse!$A$5:$A$604,"<="&DATE(Paramètres!$B$4,12,31)) | E11: =B11+C11-D11 | F11: =IF(B11=0,"",E11/B11) | G11: =SUMIFS(Clôtures!$E$5:$E$404,Clôtures!$I$5:$I$404,7,Clôtures!$A$5:$A$404,">="&DATE(Paramètres!$B$4,1,1),Clôtures!$A$5:$A$404,"<="&DATE(Paramètres!$B$4,12,31)) | H11: =SUMIFS(Avances!$D$5:$D$304,Avances!$G$5:$G$304,7,Avances!$A$5:$A$304,">="&DATE(Paramètres!$B$4,1,1),Avances!$A$5:$A$304,"<="&DATE(Paramètres!$B$4,12,31)) | I11: =SUMIFS(Caisse!$H$5:$H$604,Caisse!$D$5:$D$604,"Achat boissons",Caisse!$J$5:$J$604,7,Caisse!$A$5:$A$604,">="&DATE(Paramètres!$B$4,1,1),Caisse!$A$5:$A$604,"<="&DATE(Paramètres!$B$4,12,31)) | J11: =SUMIFS(Caisse!$H$5:$H$604,Caisse!$D$5:$D$604,"Achat cuisine / denrées",Caisse!$J$5:$J$604,7,Caisse!$A$5:$A$604,">="&DATE(Paramètres!$B$4,1,1),Caisse!$A$5:$A$604,"<="&DATE(Paramètres!$B$4,12,31)) | K11: =SUMIFS(Caisse!$H$5:$H$604,Caisse!$D$5:$D$604,"Salaire / avance",Caisse!$J$5:$J$604,7,Caisse!$A$5:$A$604,">="&DATE(Paramètres!$B$4,1,1),Caisse!$A$5:$A$604,"<="&DATE(Paramètres!$B$4,12,31)) | L11: =SUMIFS(Caisse!$H$5:$H$604,Caisse!$D$5:$D$604,"Loyer",Caisse!$J$5:$J$604,7,Caisse!$A$5:$A$604,">="&DATE(Paramètres!$B$4,1,1),Caisse!$A$5:$A$604,"<="&DATE(Paramètres!$B$4,12,31)) | M11: =SUMIFS(Caisse!$H$5:$H$604,Caisse!$D$5:$D$604,"Électricité / eau",Caisse!$J$5:$J$604,7,Caisse!$A$5:$A$604,">="&DATE(Paramètres!$B$4,1,1),Caisse!$A$5:$A$604,"<="&DATE(Paramètres!$B$4,12,31)) | N11: =SUMIFS(Caisse!$H$5:$H$604,Caisse!$D$5:$D$604,"Transport",Caisse!$J$5:$J$604,7,Caisse!$A$5:$A$604,">="&DATE(Paramètres!$B$4,1,1),Caisse!$A$5:$A$604,"<="&DATE(Paramètres!$B$4,12,31)) | O11: =SUMIFS(Caisse!$H$5:$H$604,Caisse!$D$5:$D$604,"Entretien / réparation",Caisse!$J$5:$J$604,7,Caisse!$A$5:$A$604,">="&DATE(Paramètres!$B$4,1,1),Caisse!$A$5:$A$604,"<="&DATE(Paramètres!$B$4,12,31)) | P11: =SUMIFS(Caisse!$H$5:$H$604,Caisse!$D$5:$D$604,"Taxes / mairie",Caisse!$J$5:$J$604,7,Caisse!$A$5:$A$604,">="&DATE(Paramètres!$B$4,1,1),Caisse!$A$5:$A$604,"<="&DATE(Paramètres!$B$4,12,31)) | Q11: =SUMIFS(Caisse!$H$5:$H$604,Caisse!$D$5:$D$604,"Autre dépense",Caisse!$J$5:$J$604,7,Caisse!$A$5:$A$604,">="&DATE(Paramètres!$B$4,1,1),Caisse!$A$5:$A$604,"<="&DATE(Paramètres!$B$4,12,31))
A12: Août | B12: =SUMIFS(Caisse!$G$5:$G$604,Caisse!$D$5:$D$604,"Ventes du jour",Caisse!$J$5:$J$604,8,Caisse!$A$5:$A$604,">="&DATE(Paramètres!$B$4,1,1),Caisse!$A$5:$A$604,"<="&DATE(Paramètres!$B$4,12,31)) | C12: =SUMIFS(Caisse!$G$5:$G$604,Caisse!$J$5:$J$604,8,Caisse!$A$5:$A$604,">="&DATE(Paramètres!$B$4,1,1),Caisse!$A$5:$A$604,"<="&DATE(Paramètres!$B$4,12,31))-B12 | D12: =SUMIFS(Caisse!$H$5:$H$604,Caisse!$J$5:$J$604,8,Caisse!$A$5:$A$604,">="&DATE(Paramètres!$B$4,1,1),Caisse!$A$5:$A$604,"<="&DATE(Paramètres!$B$4,12,31)) | E12: =B12+C12-D12 | F12: =IF(B12=0,"",E12/B12) | G12: =SUMIFS(Clôtures!$E$5:$E$404,Clôtures!$I$5:$I$404,8,Clôtures!$A$5:$A$404,">="&DATE(Paramètres!$B$4,1,1),Clôtures!$A$5:$A$404,"<="&DATE(Paramètres!$B$4,12,31)) | H12: =SUMIFS(Avances!$D$5:$D$304,Avances!$G$5:$G$304,8,Avances!$A$5:$A$304,">="&DATE(Paramètres!$B$4,1,1),Avances!$A$5:$A$304,"<="&DATE(Paramètres!$B$4,12,31)) | I12: =SUMIFS(Caisse!$H$5:$H$604,Caisse!$D$5:$D$604,"Achat boissons",Caisse!$J$5:$J$604,8,Caisse!$A$5:$A$604,">="&DATE(Paramètres!$B$4,1,1),Caisse!$A$5:$A$604,"<="&DATE(Paramètres!$B$4,12,31)) | J12: =SUMIFS(Caisse!$H$5:$H$604,Caisse!$D$5:$D$604,"Achat cuisine / denrées",Caisse!$J$5:$J$604,8,Caisse!$A$5:$A$604,">="&DATE(Paramètres!$B$4,1,1),Caisse!$A$5:$A$604,"<="&DATE(Paramètres!$B$4,12,31)) | K12: =SUMIFS(Caisse!$H$5:$H$604,Caisse!$D$5:$D$604,"Salaire / avance",Caisse!$J$5:$J$604,8,Caisse!$A$5:$A$604,">="&DATE(Paramètres!$B$4,1,1),Caisse!$A$5:$A$604,"<="&DATE(Paramètres!$B$4,12,31)) | L12: =SUMIFS(Caisse!$H$5:$H$604,Caisse!$D$5:$D$604,"Loyer",Caisse!$J$5:$J$604,8,Caisse!$A$5:$A$604,">="&DATE(Paramètres!$B$4,1,1),Caisse!$A$5:$A$604,"<="&DATE(Paramètres!$B$4,12,31)) | M12: =SUMIFS(Caisse!$H$5:$H$604,Caisse!$D$5:$D$604,"Électricité / eau",Caisse!$J$5:$J$604,8,Caisse!$A$5:$A$604,">="&DATE(Paramètres!$B$4,1,1),Caisse!$A$5:$A$604,"<="&DATE(Paramètres!$B$4,12,31)) | N12: =SUMIFS(Caisse!$H$5:$H$604,Caisse!$D$5:$D$604,"Transport",Caisse!$J$5:$J$604,8,Caisse!$A$5:$A$604,">="&DATE(Paramètres!$B$4,1,1),Caisse!$A$5:$A$604,"<="&DATE(Paramètres!$B$4,12,31)) | O12: =SUMIFS(Caisse!$H$5:$H$604,Caisse!$D$5:$D$604,"Entretien / réparation",Caisse!$J$5:$J$604,8,Caisse!$A$5:$A$604,">="&DATE(Paramètres!$B$4,1,1),Caisse!$A$5:$A$604,"<="&DATE(Paramètres!$B$4,12,31)) | P12: =SUMIFS(Caisse!$H$5:$H$604,Caisse!$D$5:$D$604,"Taxes / mairie",Caisse!$J$5:$J$604,8,Caisse!$A$5:$A$604,">="&DATE(Paramètres!$B$4,1,1),Caisse!$A$5:$A$604,"<="&DATE(Paramètres!$B$4,12,31)) | Q12: =SUMIFS(Caisse!$H$5:$H$604,Caisse!$D$5:$D$604,"Autre dépense",Caisse!$J$5:$J$604,8,Caisse!$A$5:$A$604,">="&DATE(Paramètres!$B$4,1,1),Caisse!$A$5:$A$604,"<="&DATE(Paramètres!$B$4,12,31))
A13: Septembre | B13: =SUMIFS(Caisse!$G$5:$G$604,Caisse!$D$5:$D$604,"Ventes du jour",Caisse!$J$5:$J$604,9,Caisse!$A$5:$A$604,">="&DATE(Paramètres!$B$4,1,1),Caisse!$A$5:$A$604,"<="&DATE(Paramètres!$B$4,12,31)) | C13: =SUMIFS(Caisse!$G$5:$G$604,Caisse!$J$5:$J$604,9,Caisse!$A$5:$A$604,">="&DATE(Paramètres!$B$4,1,1),Caisse!$A$5:$A$604,"<="&DATE(Paramètres!$B$4,12,31))-B13 | D13: =SUMIFS(Caisse!$H$5:$H$604,Caisse!$J$5:$J$604,9,Caisse!$A$5:$A$604,">="&DATE(Paramètres!$B$4,1,1),Caisse!$A$5:$A$604,"<="&DATE(Paramètres!$B$4,12,31)) | E13: =B13+C13-D13 | F13: =IF(B13=0,"",E13/B13) | G13: =SUMIFS(Clôtures!$E$5:$E$404,Clôtures!$I$5:$I$404,9,Clôtures!$A$5:$A$404,">="&DATE(Paramètres!$B$4,1,1),Clôtures!$A$5:$A$404,"<="&DATE(Paramètres!$B$4,12,31)) | H13: =SUMIFS(Avances!$D$5:$D$304,Avances!$G$5:$G$304,9,Avances!$A$5:$A$304,">="&DATE(Paramètres!$B$4,1,1),Avances!$A$5:$A$304,"<="&DATE(Paramètres!$B$4,12,31)) | I13: =SUMIFS(Caisse!$H$5:$H$604,Caisse!$D$5:$D$604,"Achat boissons",Caisse!$J$5:$J$604,9,Caisse!$A$5:$A$604,">="&DATE(Paramètres!$B$4,1,1),Caisse!$A$5:$A$604,"<="&DATE(Paramètres!$B$4,12,31)) | J13: =SUMIFS(Caisse!$H$5:$H$604,Caisse!$D$5:$D$604,"Achat cuisine / denrées",Caisse!$J$5:$J$604,9,Caisse!$A$5:$A$604,">="&DATE(Paramètres!$B$4,1,1),Caisse!$A$5:$A$604,"<="&DATE(Paramètres!$B$4,12,31)) | K13: =SUMIFS(Caisse!$H$5:$H$604,Caisse!$D$5:$D$604,"Salaire / avance",Caisse!$J$5:$J$604,9,Caisse!$A$5:$A$604,">="&DATE(Paramètres!$B$4,1,1),Caisse!$A$5:$A$604,"<="&DATE(Paramètres!$B$4,12,31)) | L13: =SUMIFS(Caisse!$H$5:$H$604,Caisse!$D$5:$D$604,"Loyer",Caisse!$J$5:$J$604,9,Caisse!$A$5:$A$604,">="&DATE(Paramètres!$B$4,1,1),Caisse!$A$5:$A$604,"<="&DATE(Paramètres!$B$4,12,31)) | M13: =SUMIFS(Caisse!$H$5:$H$604,Caisse!$D$5:$D$604,"Électricité / eau",Caisse!$J$5:$J$604,9,Caisse!$A$5:$A$604,">="&DATE(Paramètres!$B$4,1,1),Caisse!$A$5:$A$604,"<="&DATE(Paramètres!$B$4,12,31)) | N13: =SUMIFS(Caisse!$H$5:$H$604,Caisse!$D$5:$D$604,"Transport",Caisse!$J$5:$J$604,9,Caisse!$A$5:$A$604,">="&DATE(Paramètres!$B$4,1,1),Caisse!$A$5:$A$604,"<="&DATE(Paramètres!$B$4,12,31)) | O13: =SUMIFS(Caisse!$H$5:$H$604,Caisse!$D$5:$D$604,"Entretien / réparation",Caisse!$J$5:$J$604,9,Caisse!$A$5:$A$604,">="&DATE(Paramètres!$B$4,1,1),Caisse!$A$5:$A$604,"<="&DATE(Paramètres!$B$4,12,31)) | P13: =SUMIFS(Caisse!$H$5:$H$604,Caisse!$D$5:$D$604,"Taxes / mairie",Caisse!$J$5:$J$604,9,Caisse!$A$5:$A$604,">="&DATE(Paramètres!$B$4,1,1),Caisse!$A$5:$A$604,"<="&DATE(Paramètres!$B$4,12,31)) | Q13: =SUMIFS(Caisse!$H$5:$H$604,Caisse!$D$5:$D$604,"Autre dépense",Caisse!$J$5:$J$604,9,Caisse!$A$5:$A$604,">="&DATE(Paramètres!$B$4,1,1),Caisse!$A$5:$A$604,"<="&DATE(Paramètres!$B$4,12,31))
A14: Octobre | B14: =SUMIFS(Caisse!$G$5:$G$604,Caisse!$D$5:$D$604,"Ventes du jour",Caisse!$J$5:$J$604,10,Caisse!$A$5:$A$604,">="&DATE(Paramètres!$B$4,1,1),Caisse!$A$5:$A$604,"<="&DATE(Paramètres!$B$4,12,31)) | C14: =SUMIFS(Caisse!$G$5:$G$604,Caisse!$J$5:$J$604,10,Caisse!$A$5:$A$604,">="&DATE(Paramètres!$B$4,1,1),Caisse!$A$5:$A$604,"<="&DATE(Paramètres!$B$4,12,31))-B14 | D14: =SUMIFS(Caisse!$H$5:$H$604,Caisse!$J$5:$J$604,10,Caisse!$A$5:$A$604,">="&DATE(Paramètres!$B$4,1,1),Caisse!$A$5:$A$604,"<="&DATE(Paramètres!$B$4,12,31)) | E14: =B14+C14-D14 | F14: =IF(B14=0,"",E14/B14) | G14: =SUMIFS(Clôtures!$E$5:$E$404,Clôtures!$I$5:$I$404,10,Clôtures!$A$5:$A$404,">="&DATE(Paramètres!$B$4,1,1),Clôtures!$A$5:$A$404,"<="&DATE(Paramètres!$B$4,12,31)) | H14: =SUMIFS(Avances!$D$5:$D$304,Avances!$G$5:$G$304,10,Avances!$A$5:$A$304,">="&DATE(Paramètres!$B$4,1,1),Avances!$A$5:$A$304,"<="&DATE(Paramètres!$B$4,12,31)) | I14: =SUMIFS(Caisse!$H$5:$H$604,Caisse!$D$5:$D$604,"Achat boissons",Caisse!$J$5:$J$604,10,Caisse!$A$5:$A$604,">="&DATE(Paramètres!$B$4,1,1),Caisse!$A$5:$A$604,"<="&DATE(Paramètres!$B$4,12,31)) | J14: =SUMIFS(Caisse!$H$5:$H$604,Caisse!$D$5:$D$604,"Achat cuisine / denrées",Caisse!$J$5:$J$604,10,Caisse!$A$5:$A$604,">="&DATE(Paramètres!$B$4,1,1),Caisse!$A$5:$A$604,"<="&DATE(Paramètres!$B$4,12,31)) | K14: =SUMIFS(Caisse!$H$5:$H$604,Caisse!$D$5:$D$604,"Salaire / avance",Caisse!$J$5:$J$604,10,Caisse!$A$5:$A$604,">="&DATE(Paramètres!$B$4,1,1),Caisse!$A$5:$A$604,"<="&DATE(Paramètres!$B$4,12,31)) | L14: =SUMIFS(Caisse!$H$5:$H$604,Caisse!$D$5:$D$604,"Loyer",Caisse!$J$5:$J$604,10,Caisse!$A$5:$A$604,">="&DATE(Paramètres!$B$4,1,1),Caisse!$A$5:$A$604,"<="&DATE(Paramètres!$B$4,12,31)) | M14: =SUMIFS(Caisse!$H$5:$H$604,Caisse!$D$5:$D$604,"Électricité / eau",Caisse!$J$5:$J$604,10,Caisse!$A$5:$A$604,">="&DATE(Paramètres!$B$4,1,1),Caisse!$A$5:$A$604,"<="&DATE(Paramètres!$B$4,12,31)) | N14: =SUMIFS(Caisse!$H$5:$H$604,Caisse!$D$5:$D$604,"Transport",Caisse!$J$5:$J$604,10,Caisse!$A$5:$A$604,">="&DATE(Paramètres!$B$4,1,1),Caisse!$A$5:$A$604,"<="&DATE(Paramètres!$B$4,12,31)) | O14: =SUMIFS(Caisse!$H$5:$H$604,Caisse!$D$5:$D$604,"Entretien / réparation",Caisse!$J$5:$J$604,10,Caisse!$A$5:$A$604,">="&DATE(Paramètres!$B$4,1,1),Caisse!$A$5:$A$604,"<="&DATE(Paramètres!$B$4,12,31)) | P14: =SUMIFS(Caisse!$H$5:$H$604,Caisse!$D$5:$D$604,"Taxes / mairie",Caisse!$J$5:$J$604,10,Caisse!$A$5:$A$604,">="&DATE(Paramètres!$B$4,1,1),Caisse!$A$5:$A$604,"<="&DATE(Paramètres!$B$4,12,31)) | Q14: =SUMIFS(Caisse!$H$5:$H$604,Caisse!$D$5:$D$604,"Autre dépense",Caisse!$J$5:$J$604,10,Caisse!$A$5:$A$604,">="&DATE(Paramètres!$B$4,1,1),Caisse!$A$5:$A$604,"<="&DATE(Paramètres!$B$4,12,31))
A15: Novembre | B15: =SUMIFS(Caisse!$G$5:$G$604,Caisse!$D$5:$D$604,"Ventes du jour",Caisse!$J$5:$J$604,11,Caisse!$A$5:$A$604,">="&DATE(Paramètres!$B$4,1,1),Caisse!$A$5:$A$604,"<="&DATE(Paramètres!$B$4,12,31)) | C15: =SUMIFS(Caisse!$G$5:$G$604,Caisse!$J$5:$J$604,11,Caisse!$A$5:$A$604,">="&DATE(Paramètres!$B$4,1,1),Caisse!$A$5:$A$604,"<="&DATE(Paramètres!$B$4,12,31))-B15 | D15: =SUMIFS(Caisse!$H$5:$H$604,Caisse!$J$5:$J$604,11,Caisse!$A$5:$A$604,">="&DATE(Paramètres!$B$4,1,1),Caisse!$A$5:$A$604,"<="&DATE(Paramètres!$B$4,12,31)) | E15: =B15+C15-D15 | F15: =IF(B15=0,"",E15/B15) | G15: =SUMIFS(Clôtures!$E$5:$E$404,Clôtures!$I$5:$I$404,11,Clôtures!$A$5:$A$404,">="&DATE(Paramètres!$B$4,1,1),Clôtures!$A$5:$A$404,"<="&DATE(Paramètres!$B$4,12,31)) | H15: =SUMIFS(Avances!$D$5:$D$304,Avances!$G$5:$G$304,11,Avances!$A$5:$A$304,">="&DATE(Paramètres!$B$4,1,1),Avances!$A$5:$A$304,"<="&DATE(Paramètres!$B$4,12,31)) | I15: =SUMIFS(Caisse!$H$5:$H$604,Caisse!$D$5:$D$604,"Achat boissons",Caisse!$J$5:$J$604,11,Caisse!$A$5:$A$604,">="&DATE(Paramètres!$B$4,1,1),Caisse!$A$5:$A$604,"<="&DATE(Paramètres!$B$4,12,31)) | J15: =SUMIFS(Caisse!$H$5:$H$604,Caisse!$D$5:$D$604,"Achat cuisine / denrées",Caisse!$J$5:$J$604,11,Caisse!$A$5:$A$604,">="&DATE(Paramètres!$B$4,1,1),Caisse!$A$5:$A$604,"<="&DATE(Paramètres!$B$4,12,31)) | K15: =SUMIFS(Caisse!$H$5:$H$604,Caisse!$D$5:$D$604,"Salaire / avance",Caisse!$J$5:$J$604,11,Caisse!$A$5:$A$604,">="&DATE(Paramètres!$B$4,1,1),Caisse!$A$5:$A$604,"<="&DATE(Paramètres!$B$4,12,31)) | L15: =SUMIFS(Caisse!$H$5:$H$604,Caisse!$D$5:$D$604,"Loyer",Caisse!$J$5:$J$604,11,Caisse!$A$5:$A$604,">="&DATE(Paramètres!$B$4,1,1),Caisse!$A$5:$A$604,"<="&DATE(Paramètres!$B$4,12,31)) | M15: =SUMIFS(Caisse!$H$5:$H$604,Caisse!$D$5:$D$604,"Électricité / eau",Caisse!$J$5:$J$604,11,Caisse!$A$5:$A$604,">="&DATE(Paramètres!$B$4,1,1),Caisse!$A$5:$A$604,"<="&DATE(Paramètres!$B$4,12,31)) | N15: =SUMIFS(Caisse!$H$5:$H$604,Caisse!$D$5:$D$604,"Transport",Caisse!$J$5:$J$604,11,Caisse!$A$5:$A$604,">="&DATE(Paramètres!$B$4,1,1),Caisse!$A$5:$A$604,"<="&DATE(Paramètres!$B$4,12,31)) | O15: =SUMIFS(Caisse!$H$5:$H$604,Caisse!$D$5:$D$604,"Entretien / réparation",Caisse!$J$5:$J$604,11,Caisse!$A$5:$A$604,">="&DATE(Paramètres!$B$4,1,1),Caisse!$A$5:$A$604,"<="&DATE(Paramètres!$B$4,12,31)) | P15: =SUMIFS(Caisse!$H$5:$H$604,Caisse!$D$5:$D$604,"Taxes / mairie",Caisse!$J$5:$J$604,11,Caisse!$A$5:$A$604,">="&DATE(Paramètres!$B$4,1,1),Caisse!$A$5:$A$604,"<="&DATE(Paramètres!$B$4,12,31)) | Q15: =SUMIFS(Caisse!$H$5:$H$604,Caisse!$D$5:$D$604,"Autre dépense",Caisse!$J$5:$J$604,11,Caisse!$A$5:$A$604,">="&DATE(Paramètres!$B$4,1,1),Caisse!$A$5:$A$604,"<="&DATE(Paramètres!$B$4,12,31))
A16: Décembre | B16: =SUMIFS(Caisse!$G$5:$G$604,Caisse!$D$5:$D$604,"Ventes du jour",Caisse!$J$5:$J$604,12,Caisse!$A$5:$A$604,">="&DATE(Paramètres!$B$4,1,1),Caisse!$A$5:$A$604,"<="&DATE(Paramètres!$B$4,12,31)) | C16: =SUMIFS(Caisse!$G$5:$G$604,Caisse!$J$5:$J$604,12,Caisse!$A$5:$A$604,">="&DATE(Paramètres!$B$4,1,1),Caisse!$A$5:$A$604,"<="&DATE(Paramètres!$B$4,12,31))-B16 | D16: =SUMIFS(Caisse!$H$5:$H$604,Caisse!$J$5:$J$604,12,Caisse!$A$5:$A$604,">="&DATE(Paramètres!$B$4,1,1),Caisse!$A$5:$A$604,"<="&DATE(Paramètres!$B$4,12,31)) | E16: =B16+C16-D16 | F16: =IF(B16=0,"",E16/B16) | G16: =SUMIFS(Clôtures!$E$5:$E$404,Clôtures!$I$5:$I$404,12,Clôtures!$A$5:$A$404,">="&DATE(Paramètres!$B$4,1,1),Clôtures!$A$5:$A$404,"<="&DATE(Paramètres!$B$4,12,31)) | H16: =SUMIFS(Avances!$D$5:$D$304,Avances!$G$5:$G$304,12,Avances!$A$5:$A$304,">="&DATE(Paramètres!$B$4,1,1),Avances!$A$5:$A$304,"<="&DATE(Paramètres!$B$4,12,31)) | I16: =SUMIFS(Caisse!$H$5:$H$604,Caisse!$D$5:$D$604,"Achat boissons",Caisse!$J$5:$J$604,12,Caisse!$A$5:$A$604,">="&DATE(Paramètres!$B$4,1,1),Caisse!$A$5:$A$604,"<="&DATE(Paramètres!$B$4,12,31)) | J16: =SUMIFS(Caisse!$H$5:$H$604,Caisse!$D$5:$D$604,"Achat cuisine / denrées",Caisse!$J$5:$J$604,12,Caisse!$A$5:$A$604,">="&DATE(Paramètres!$B$4,1,1),Caisse!$A$5:$A$604,"<="&DATE(Paramètres!$B$4,12,31)) | K16: =SUMIFS(Caisse!$H$5:$H$604,Caisse!$D$5:$D$604,"Salaire / avance",Caisse!$J$5:$J$604,12,Caisse!$A$5:$A$604,">="&DATE(Paramètres!$B$4,1,1),Caisse!$A$5:$A$604,"<="&DATE(Paramètres!$B$4,12,31)) | L16: =SUMIFS(Caisse!$H$5:$H$604,Caisse!$D$5:$D$604,"Loyer",Caisse!$J$5:$J$604,12,Caisse!$A$5:$A$604,">="&DATE(Paramètres!$B$4,1,1),Caisse!$A$5:$A$604,"<="&DATE(Paramètres!$B$4,12,31)) | M16: =SUMIFS(Caisse!$H$5:$H$604,Caisse!$D$5:$D$604,"Électricité / eau",Caisse!$J$5:$J$604,12,Caisse!$A$5:$A$604,">="&DATE(Paramètres!$B$4,1,1),Caisse!$A$5:$A$604,"<="&DATE(Paramètres!$B$4,12,31)) | N16: =SUMIFS(Caisse!$H$5:$H$604,Caisse!$D$5:$D$604,"Transport",Caisse!$J$5:$J$604,12,Caisse!$A$5:$A$604,">="&DATE(Paramètres!$B$4,1,1),Caisse!$A$5:$A$604,"<="&DATE(Paramètres!$B$4,12,31)) | O16: =SUMIFS(Caisse!$H$5:$H$604,Caisse!$D$5:$D$604,"Entretien / réparation",Caisse!$J$5:$J$604,12,Caisse!$A$5:$A$604,">="&DATE(Paramètres!$B$4,1,1),Caisse!$A$5:$A$604,"<="&DATE(Paramètres!$B$4,12,31)) | P16: =SUMIFS(Caisse!$H$5:$H$604,Caisse!$D$5:$D$604,"Taxes / mairie",Caisse!$J$5:$J$604,12,Caisse!$A$5:$A$604,">="&DATE(Paramètres!$B$4,1,1),Caisse!$A$5:$A$604,"<="&DATE(Paramètres!$B$4,12,31)) | Q16: =SUMIFS(Caisse!$H$5:$H$604,Caisse!$D$5:$D$604,"Autre dépense",Caisse!$J$5:$J$604,12,Caisse!$A$5:$A$604,">="&DATE(Paramètres!$B$4,1,1),Caisse!$A$5:$A$604,"<="&DATE(Paramètres!$B$4,12,31))
A17: TOTAL | B17: =SUM(B5:B16) | C17: =SUM(C5:C16) | D17: =SUM(D5:D16) | E17: =SUM(E5:E16) | F17: =IF(B17=0,"",E17/B17) | G17: =SUM(G5:G16) | H17: =SUM(H5:H16) | I17: =SUM(I5:I16) | J17: =SUM(J5:J16) | K17: =SUM(K5:K16) | L17: =SUM(L5:L16) | M17: =SUM(M5:M16) | N17: =SUM(N5:N16) | ... Q17: =SUM(Q5:Q16)
A20: Crédits clients en cours | B20: =SUM('Crédits clients'!$I$5:$I$304)
A21: Valeur du stock | B21: =SUM(Stocks!$O$5:$O$154)
A22: Articles à commander | B22: =COUNTIF(Stocks!$R$5:$R$154,"À COMMANDER")

Sheet Paramètres
A1: La Tendresse de Ketchup — Paramètres
D3: Catégories entrées | E3: Catégories sorties | F3: Modes de paiement | G3: Personnel | H3: Toutes catégories
A4: Année suivie | B4: 2026 | D4: Ventes du jour | E4: Achat boissons | F4: Espèces | H4: Ventes du jour
A5: Fonds de caisse de départ | B5: 0 | D5: Remboursement crédit client | E5: Achat cuisine / denrées | F5: MTN MoMo | H5: Remboursement crédit client
A6: Seuil d'alerte écart de caisse | B6: 2000 | D6: Apport du gérant / propriétaire | E6: Salaire / avance | F6: Airtel Money | H6: Apport du gérant / propriétaire
D7: Vente d'emballages vides | E7: Loyer | F7: Autre | H7: Vente d'emballages vides
D8: Autre entrée | E8: Électricité / eau | H8: Autre entrée
E9: Transport | H9: Achat boissons
E10: Entretien / réparation | H10: Achat cuisine / denrées
E11: Taxes / mairie | H11: Salaire / avance
E12: Autre dépense | H12: Loyer
H13: Électricité / eau
H14: Transport
H15: Entretien / réparation
H16: Taxes / mairie
H17: Autre dépense

Sheet Caisse
A1: La Tendresse de Ketchup — Journal de caisse
A2: Une ligne par pièce de caisse. Le solde se calcule à partir du fonds de départ (Paramètres).
A4: Date | B4: N° pièce | C4: Type | D4: Catégorie | E4: Libellé | F4: Mode | G4: Entrée FCFA | H4: Sortie FCFA | I4: Solde FCFA | J4: Mois
I5: =IF(AND(G5="",H5=""),"",Paramètres!$B$5+SUM(G$5:G5)-SUM(H$5:H5)) | J5: =IF(A5="","",MONTH(A5))
I6: =IF(AND(G6="",H6=""),"",Paramètres!$B$5+SUM(G$5:G6)-SUM(H$5:H6)) | J6: =IF(A6="","",MONTH(A6))
I7: =IF(AND(G7="",H7=""),"",Paramètres!$B$5+SUM(G$5:G7)-SUM(H$5:H7)) | J7: =IF(A7="","",MONTH(A7))
I8: =IF(AND(G8="",H8=""),"",Paramètres!$B$5+SUM(G$5:G8)-SUM(H$5:H8)) | J8: =IF(A8="","",MONTH(A8))
I9: =IF(AND(G9="",H9=""),"",Paramètres!$B$5+SUM(G$5:G9)-SUM(H$5:H9)) | J9: =IF(A9="","",MONTH(A9))
I10: =IF(AND(G10="",H10=""),"",Paramètres!$B$5+SUM(G$5:G10)-SUM(H$5:H10)) | J10: =IF(A10="","",MONTH(A10))
I11: =IF(AND(G11="",H11=""),"",Paramètres!$B$5+SUM(G$5:G11)-SUM(H$5:H11)) | J11: =IF(A11="","",MONTH(A11))
I12: =IF(AND(G12="",H12=""),"",Paramètres!$B$5+SUM(G$5:G12)-SUM(H$5:H12)) | J12: =IF(A12="","",MONTH(A12))
I13: =IF(AND(G13="",H13=""),"",Paramètres!$B$5+SUM(G$5:G13)-SUM(H$5:H13)) | J13: =IF(A13="","",MONTH(A13))
I14: =IF(AND(G14="",H14=""),"",Paramètres!$B$5+SUM(G$5:G14)-SUM(H$5:H14)) | J14: =IF(A14="","",MONTH(A14))
I15: =IF(AND(G15="",H15=""),"",Paramètres!$B$5+SUM(G$5:G15)-SUM(H$5:H15)) | J15: =IF(A15="","",MONTH(A15))
I16: =IF(AND(G16="",H16=""),"",Paramètres!$B$5+SUM(G$5:G16)-SUM(H$5:H16)) | J16: =IF(A16="","",MONTH(A16))
... I604: =IF(AND(G604="",H604=""),"",Paramètres!$B$5+SUM(G$5:G604)-SUM(H$5:H604)) | J604: =IF(A604="","",MONTH(A604))

Sheet Clôtures
A1: La Tendresse de Ketchup — Clôtures de caisse
A2: Reporter chaque soir la fiche de clôture.
A4: Date | B4: Caissier(ère) | C4: Solde théorique FCFA | D4: Espèces comptées FCFA | E4: Écart FCFA | F4: MoMo / Airtel FCFA | G4: Versé FCFA | H4: Explication | I4: Mois
E5: =IF(D5="","",D5-C5) | I5: =IF(A5="","",MONTH(A5))
E6: =IF(D6="","",D6-C6) | I6: =IF(A6="","",MONTH(A6))
E7: =IF(D7="","",D7-C7) | I7: =IF(A7="","",MONTH(A7))
E8: =IF(D8="","",D8-C8) | I8: =IF(A8="","",MONTH(A8))
E9: =IF(D9="","",D9-C9) | I9: =IF(A9="","",MONTH(A9))
E10: =IF(D10="","",D10-C10) | I10: =IF(A10="","",MONTH(A10))
E11: =IF(D11="","",D11-C11) | I11: =IF(A11="","",MONTH(A11))
E12: =IF(D12="","",D12-C12) | I12: =IF(A12="","",MONTH(A12))
E13: =IF(D13="","",D13-C13) | I13: =IF(A13="","",MONTH(A13))
E14: =IF(D14="","",D14-C14) | I14: =IF(A14="","",MONTH(A14))
E15: =IF(D15="","",D15-C15) | I15: =IF(A15="","",MONTH(A15))
E16: =IF(D16="","",D16-C16) | I16: =IF(A16="","",MONTH(A16))
... E404: =IF(D404="","",D404-C404) | I404: =IF(A404="","",MONTH(A404))

Sheet Stocks
A1: La Tendresse de Ketchup — Stocks et marges
A2: Une ligne par article. Mettre à jour à chaque inventaire hebdomadaire.
A4: Article | B4: Catégorie | C4: Unité | D4: Prix d'achat FCFA | E4: Prix de vente FCFA | F4: Stock mini | G4: Stock initial | H4: Entrées | I4: Ventes | J4: Casses / offerts | K4: Stock théorique | L4: Stock compté | M4: Écart | N4: Valeur écart FCFA | O4: Valeur stock FCFA | P4: Marge / unité FCFA | Q4: Taux de marge | R4: Alerte
A5: Bière 65 cl (à préciser) | B5: Bières | C5: Bouteille | K5: =IF(A5="","",N(G5)+N(H5)-N(I5)-N(J5)) | M5: =IF(L5="","",L5-K5) | N5: =IF(M5="","",M5*N(E5)) | O5: =IF(A5="","",IF(L5="",K5,L5)*N(D5)) | P5: =IF(OR(D5="",E5=""),"",E5-D5) | Q5: =IF(OR(N(E5)=0,P5=""),"",P5/E5) | R5: =IF(OR(A5="",F5=""),"",IF(IF(L5="",K5,L5)<=F5,"À COMMANDER","OK"))
A6: Bière 50 cl (à préciser) | B6: Bières | C6: Bouteille | K6: =IF(A6="","",N(G6)+N(H6)-N(I6)-N(J6)) | M6: =IF(L6="","",L6-K6) | N6: =IF(M6="","",M6*N(E6)) | O6: =IF(A6="","",IF(L6="",K6,L6)*N(D6)) | P6: =IF(OR(D6="",E6=""),"",E6-D6) | Q6: =IF(OR(N(E6)=0,P6=""),"",P6/E6) | R6: =IF(OR(A6="",F6=""),"",IF(IF(L6="",K6,L6)<=F6,"À COMMANDER","OK"))
A7: Boisson sucrée 33 cl | B7: Sucreries & eaux | C7: Bouteille | K7: =IF(A7="","",N(G7)+N(H7)-N(I7)-N(J7)) | M7: =IF(L7="","",L7-K7) | N7: =IF(M7="","",M7*N(E7)) | O7: =IF(A7="","",IF(L7="",K7,L7)*N(D7)) | P7: =IF(OR(D7="",E7=""),"",E7-D7) | Q7: =IF(OR(N(E7)=0,P7=""),"",P7/E7) | R7: =IF(OR(A7="",F7=""),"",IF(IF(L7="",K7,L7)<=F7,"À COMMANDER","OK"))
A8: Eau minérale 1,5 L | B8: Sucreries & eaux | C8: Bouteille | K8: =IF(A8="","",N(G8)+N(H8)-N(I8)-N(J8)) | M8: =IF(L8="","",L8-K8) | N8: =IF(M8="","",M8*N(E8)) | O8: =IF(A8="","",IF(L8="",K8,L8)*N(D8)) | P8: =IF(OR(D8="",E8=""),"",E8-D8) | Q8: =IF(OR(N(E8)=0,P8=""),"",P8/E8) | R8: =IF(OR(A8="",F8=""),"",IF(IF(L8="",K8,L8)<=F8,"À COMMANDER","OK"))
A9: Vin rouge 75 cl | B9: Vins & spiritueux | C9: Bouteille | K9: =IF(A9="","",N(G9)+N(H9)-N(I9)-N(J9)) | M9: =IF(L9="","",L9-K9) | N9: =IF(M9="","",M9*N(E9)) | O9: =IF(A9="","",IF(L9="",K9,L9)*N(D9)) | P9: =IF(OR(D9="",E9=""),"",E9-D9) | Q9: =IF(OR(N(E9)=0,P9=""),"",P9/E9) | R9: =IF(OR(A9="",F9=""),"",IF(IF(L9="",K9,L9)<=F9,"À COMMANDER","OK"))
A10: Whisky 70 cl | B10: Vins & spiritueux | C10: Bouteille | K10: =IF(A10="","",N(G10)+N(H10)-N(I10)-N(J10)) | M10: =IF(L10="","",L10-K10) | N10: =IF(M10="","",M10*N(E10)) | O10: =IF(A10="","",IF(L10="",K10,L10)*N(D10)) | P10: =IF(OR(D10="",E10=""),"",E10-D10) | Q10: =IF(OR(N(E10)=0,P10=""),"",P10/E10) | R10: =IF(OR(A10="",F10=""),"",IF(IF(L10="",K10,L10)<=F10,"À COMMANDER","OK"))
K11: =IF(A11="","",N(G11)+N(H11)-N(I11)-N(J11)) | M11: =IF(L11="","",L11-K11) | N11: =IF(M11="","",M11*N(E11)) | O11: =IF(A11="","",IF(L11="",K11,L11)*N(D11)) | P11: =IF(OR(D11="",E11=""),"",E11-D11) | Q11: =IF(OR(N(E11)=0,P11=""),"",P11/E11) | R11: =IF(OR(A11="",F11=""),"",IF(IF(L11="",K11,L11)<=F11,"À COMMANDER","OK"))
K12: =IF(A12="","",N(G12)+N(H12)-N(I12)-N(J12)) | M12: =IF(L12="","",L12-K12) | N12: =IF(M12="","",M12*N(E12)) | O12: =IF(A12="","",IF(L12="",K12,L12)*N(D12)) | P12: =IF(OR(D12="",E12=""),"",E12-D12) | Q12: =IF(OR(N(E12)=0,P12=""),"",P12/E12) | R12: =IF(OR(A12="",F12=""),"",IF(IF(L12="",K12,L12)<=F12,"À COMMANDER","OK"))
K13: =IF(A13="","",N(G13)+N(H13)-N(I13)-N(J13)) | M13: =IF(L13="","",L13-K13) | N13: =IF(M13="","",M13*N(E13)) | O13: =IF(A13="","",IF(L13="",K13,L13)*N(D13)) | P13: =IF(OR(D13="",E13=""),"",E13-D13) | Q13: =IF(OR(N(E13)=0,P13=""),"",P13/E13) | R13: =IF(OR(A13="",F13=""),"",IF(IF(L13="",K13,L13)<=F13,"À COMMANDER","OK"))
K14: =IF(A14="","",N(G14)+N(H14)-N(I14)-N(J14)) | M14: =IF(L14="","",L14-K14) | N14: =IF(M14="","",M14*N(E14)) | O14: =IF(A14="","",IF(L14="",K14,L14)*N(D14)) | P14: =IF(OR(D14="",E14=""),"",E14-D14) | Q14: =IF(OR(N(E14)=0,P14=""),"",P14/E14) | R14: =IF(OR(A14="",F14=""),"",IF(IF(L14="",K14,L14)<=F14,"À COMMANDER","OK"))
K15: =IF(A15="","",N(G15)+N(H15)-N(I15)-N(J15)) | M15: =IF(L15="","",L15-K15) | N15: =IF(M15="","",M15*N(E15)) | O15: =IF(A15="","",IF(L15="",K15,L15)*N(D15)) | P15: =IF(OR(D15="",E15=""),"",E15-D15) | Q15: =IF(OR(N(E15)=0,P15=""),"",P15/E15) | R15: =IF(OR(A15="",F15=""),"",IF(IF(L15="",K15,L15)<=F15,"À COMMANDER","OK"))
K16: =IF(A16="","",N(G16)+N(H16)-N(I16)-N(J16)) | M16: =IF(L16="","",L16-K16) | N16: =IF(M16="","",M16*N(E16)) | O16: =IF(A16="","",IF(L16="",K16,L16)*N(D16)) | P16: =IF(OR(D16="",E16=""),"",E16-D16) | Q16: =IF(OR(N(E16)=0,P16=""),"",P16/E16) | R16: =IF(OR(A16="",F16=""),"",IF(IF(L16="",K16,L16)<=F16,"À COMMANDER","OK"))
K17: =IF(A17="","",N(G17)+N(H17)-N(I17)-N(J17)) | M17: =IF(L17="","",L17-K17) | N17: =IF(M17="","",M17*N(E17)) | O17: =IF(A17="","",IF(L17="",K17,L17)*N(D17)) | P17: =IF(OR(D17="",E17=""),"",E17-D17) | Q17: =IF(OR(N(E17)=0,P17=""),"",P17/E17) | R17: =IF(OR(A17="",F17=""),"",IF(IF(L17="",K17,L17)<=F17,"À COMMANDER","OK"))
K18: =IF(A18="","",N(G18)+N(H18)-N(I18)-N(J18)) | M18: =IF(L18="","",L18-K18) | N18: =IF(M18="","",M18*N(E18)) | O18: =IF(A18="","",IF(L18="",K18,L18)*N(D18)) | P18: =IF(OR(D18="",E18=""),"",E18-D18) | Q18: =IF(OR(N(E18)=0,P18=""),"",P18/E18) | R18: =IF(OR(A18="",F18=""),"",IF(IF(L18="",K18,L18)<=F18,"À COMMANDER","OK"))
K19: =IF(A19="","",N(G19)+N(H19)-N(I19)-N(J19)) | M19: =IF(L19="","",L19-K19) | N19: =IF(M19="","",M19*N(E19)) | O19: =IF(A19="","",IF(L19="",K19,L19)*N(D19)) | P19: =IF(OR(D19="",E19=""),"",E19-D19) | Q19: =IF(OR(N(E19)=0,P19=""),"",P19/E19) | R19: =IF(OR(A19="",F19=""),"",IF(IF(L19="",K19,L19)<=F19,"À COMMANDER","OK"))
K20: =IF(A20="","",N(G20)+N(H20)-N(I20)-N(J20)) | M20: =IF(L20="","",L20-K20) | N20: =IF(M20="","",M20*N(E20)) | O20: =IF(A20="","",IF(L20="",K20,L20)*N(D20)) | P20: =IF(OR(D20="",E20=""),"",E20-D20) | Q20: =IF(OR(N(E20)=0,P20=""),"",P20/E20) | R20: =IF(OR(A20="",F20=""),"",IF(IF(L20="",K20,L20)<=F20,"À COMMANDER","OK"))
K21: =IF(A21="","",N(G21)+N(H21)-N(I21)-N(J21)) | M21: =IF(L21="","",L21-K21) | N21: =IF(M21="","",M21*N(E21)) | O21: =IF(A21="","",IF(L21="",K21,L21)*N(D21)) | P21: =IF(OR(D21="",E21=""),"",E21-D21) | Q21: =IF(OR(N(E21)=0,P21=""),"",P21/E21) | R21: =IF(OR(A21="",F21=""),"",IF(IF(L21="",K21,L21)<=F21,"À COMMANDER","OK"))
K22: =IF(A22="","",N(G22)+N(H22)-N(I22)-N(J22)) | M22: =IF(L22="","",L22-K22) | N22: =IF(M22="","",M22*N(E22)) | O22: =IF(A22="","",IF(L22="",K22,L22)*N(D22)) | P22: =IF(OR(D22="",E22=""),"",E22-D22) | Q22: =IF(OR(N(E22)=0,P22=""),"",P22/E22) | R22: =IF(OR(A22="",F22=""),"",IF(IF(L22="",K22,L22)<=F22,"À COMMANDER","OK"))
... K154: =IF(A154="","",N(G154)+N(H154)-N(I154)-N(J154)) | M154: =IF(L154="","",L154-K154) | N154: =IF(M154="","",M154*N(E154)) | O154: =IF(A154="","",IF(L154="",K154,L154)*N(D154)) | P154: =IF(OR(D154="",E154=""),"",E154-D154) | Q154: =IF(OR(N(E154)=0,P154=""),"",P154/E154) | R154: =IF(OR(A154="",F154=""),"",IF(IF(L154="",K154,L154)<=F154,"À COMMANDER","OK"))

Sheet Crédits clients
A1: La Tendresse de Ketchup — Crédits clients
A2: Crédit exceptionnel, accordé par la Direction uniquement.
A4: N° | B4: Date | C4: Client | D4: Téléphone | E4: Détail | F4: Montant FCFA | G4: Échéance | H4: Remboursé FCFA | I4: Reste dû FCFA | J4: Statut
I5: =IF(F5="","",F5-N(H5)) | J5: =IF(F5="","",IF(I5<=0,"Soldé",IF(AND(G5<>"",TODAY()>G5),"EN RETARD","En cours")))
I6: =IF(F6="","",F6-N(H6)) | J6: =IF(F6="","",IF(I6<=0,"Soldé",IF(AND(G6<>"",TODAY()>G6),"EN RETARD","En cours")))
I7: =IF(F7="","",F7-N(H7)) | J7: =IF(F7="","",IF(I7<=0,"Soldé",IF(AND(G7<>"",TODAY()>G7),"EN RETARD","En cours")))
I8: =IF(F8="","",F8-N(H8)) | J8: =IF(F8="","",IF(I8<=0,"Soldé",IF(AND(G8<>"",TODAY()>G8),"EN RETARD","En cours")))
I9: =IF(F9="","",F9-N(H9)) | J9: =IF(F9="","",IF(I9<=0,"Soldé",IF(AND(G9<>"",TODAY()>G9),"EN RETARD","En cours")))
I10: =IF(F10="","",F10-N(H10)) | J10: =IF(F10="","",IF(I10<=0,"Soldé",IF(AND(G10<>"",TODAY()>G10),"EN RETARD","En cours")))
I11: =IF(F11="","",F11-N(H11)) | J11: =IF(F11="","",IF(I11<=0,"Soldé",IF(AND(G11<>"",TODAY()>G11),"EN RETARD","En cours")))
I12: =IF(F12="","",F12-N(H12)) | J12: =IF(F12="","",IF(I12<=0,"Soldé",IF(AND(G12<>"",TODAY()>G12),"EN RETARD","En cours")))
I13: =IF(F13="","",F13-N(H13)) | J13: =IF(F13="","",IF(I13<=0,"Soldé",IF(AND(G13<>"",TODAY()>G13),"EN RETARD","En cours")))
I14: =IF(F14="","",F14-N(H14)) | J14: =IF(F14="","",IF(I14<=0,"Soldé",IF(AND(G14<>"",TODAY()>G14),"EN RETARD","En cours")))
I15: =IF(F15="","",F15-N(H15)) | J15: =IF(F15="","",IF(I15<=0,"Soldé",IF(AND(G15<>"",TODAY()>G15),"EN RETARD","En cours")))
I16: =IF(F16="","",F16-N(H16)) | J16: =IF(F16="","",IF(I16<=0,"Soldé",IF(AND(G16<>"",TODAY()>G16),"EN RETARD","En cours")))
... I304: =IF(F304="","",F304-N(H304)) | J304: =IF(F304="","",IF(I304<=0,"Soldé",IF(AND(G304<>"",TODAY()>G304),"EN RETARD","En cours")))

Sheet Avances
A1: La Tendresse de Ketchup — Avances sur salaire
A2: Reporter les bons d'avance. Le total du mois est retenu sur la fiche de paiement.
A4: Date | B4: N° bon | C4: Employé(e) | D4: Montant FCFA | E4: Mois de retenue (1-12) | F4: Retenu ? (Oui/Non) | G4: Mois
G5: =IF(A5="","",MONTH(A5))
G6: =IF(A6="","",MONTH(A6))
G7: =IF(A7="","",MONTH(A7))
G8: =IF(A8="","",MONTH(A8))
G9: =IF(A9="","",MONTH(A9))
G10: =IF(A10="","",MONTH(A10))
G11: =IF(A11="","",MONTH(A11))
G12: =IF(A12="","",MONTH(A12))
G13: =IF(A13="","",MONTH(A13))
G14: =IF(A14="","",MONTH(A14))
G15: =IF(A15="","",MONTH(A15))
G16: =IF(A16="","",MONTH(A16))
... G304: =IF(A304="","",MONTH(A304))
